asciify/__init__.py
asciify/charsets.py
asciify/cli.py
asciify/converter.py
asciify_image-0.1.0.dist-info/METADATA
asciify_image-0.1.0.dist-info/WHEEL
asciify_image-0.1.0.dist-info/entry_points.txt
asciify_image-0.1.0.dist-info/licenses/LICENSE
asciify_image-0.1.0.dist-info/RECORD
