Metadata-Version: 2.4
Name: asciify-image
Version: 0.1.0
Summary: Convert images to ASCII art with color, dithering, and multiple character sets
Project-URL: Homepage, https://github.com/visakhunnikrishnan/asciify
Project-URL: Repository, https://github.com/visakhunnikrishnan/asciify
Project-URL: Issues, https://github.com/visakhunnikrishnan/asciify/issues
Author-email: Visakh Unni <contact@visakhunni.com>
License-Expression: MIT
License-File: LICENSE
Keywords: ascii,ascii-art,cli,converter,image,terminal
Classifier: Development Status :: 4 - Beta
Classifier: Environment :: Console
Classifier: Intended Audience :: Developers
Classifier: Intended Audience :: End Users/Desktop
Classifier: License :: OSI Approved :: MIT License
Classifier: Operating System :: OS Independent
Classifier: Programming Language :: Python :: 3
Classifier: Programming Language :: Python :: 3.9
Classifier: Programming Language :: Python :: 3.10
Classifier: Programming Language :: Python :: 3.11
Classifier: Programming Language :: Python :: 3.12
Classifier: Programming Language :: Python :: 3.13
Classifier: Topic :: Artistic Software
Classifier: Topic :: Multimedia :: Graphics :: Graphics Conversion
Classifier: Topic :: Terminals
Requires-Python: >=3.9
Requires-Dist: numpy>=1.20.0
Requires-Dist: pillow>=9.0.0
Provides-Extra: dev
Requires-Dist: mypy>=1.0.0; extra == 'dev'
Requires-Dist: pytest-cov>=4.0.0; extra == 'dev'
Requires-Dist: pytest>=7.0.0; extra == 'dev'
Requires-Dist: ruff>=0.1.0; extra == 'dev'
